one_to_one.py
semantic_model.py
semantic_model-3.0.0.dist-info/LICENSE
semantic_model-3.0.0.dist-info/METADATA
semantic_model-3.0.0.dist-info/WHEEL
semantic_model-3.0.0.dist-info/top_level.txt
semantic_model-3.0.0.dist-info/RECORD
