Metadata-Version: 2.1
Name: semantic-model
Version: 3.0.0
Summary: All data about data in one model
Home-page: https://github.com/Attumm/semantic-model
Author: Melvin Bijman
Author-email: bijman.m.m@gmail.com
License: MIT
Classifier: Development Status :: 5 - Production/Stable
Classifier: Intended Audience :: Developers
Classifier: License :: OSI Approved :: MIT License
Classifier: Programming Language :: Python :: 3
Classifier: Programming Language :: Python :: 3.5
Classifier: Programming Language :: Python :: 3.6
Classifier: Programming Language :: Python :: 3.7
Classifier: Programming Language :: Python :: 3.8
Classifier: Programming Language :: Python :: 3.9
Classifier: Programming Language :: Python :: 3.10
Classifier: Programming Language :: Python :: 3.11
License-File: LICENSE
Requires-Dist: settipy
